DjangoExampleApplication/__init__.py
DjangoExampleApplication/admin.py
DjangoExampleApplication/apps.py
DjangoExampleApplication/models.py
DjangoExampleApplication/tests.py
DjangoExampleApplication/migrations/0001_initial.py
DjangoExampleApplication/migrations/0002_auto_20210313_1049.py
DjangoExampleApplication/migrations/0003_genericattachment.py
DjangoExampleApplication/migrations/__init__.py
DjangoExampleProject/__init__.py
DjangoExampleProject/asgi.py
DjangoExampleProject/settings.py
DjangoExampleProject/urls.py
DjangoExampleProject/wsgi.py
django_minio_backend/__init__.py
django_minio_backend/apps.py
django_minio_backend/models.py
django_minio_backend/tests.py
django_minio_backend/utils.py
django_minio_backend/management/__init__.py
django_minio_backend/management/commands/__init__.py
django_minio_backend/management/commands/initialize_buckets.py
django_minio_backend/management/commands/is_minio_available.py
django_minio_backend_five-3.5.3.dist-info/LICENSE
django_minio_backend_five-3.5.3.dist-info/METADATA
django_minio_backend_five-3.5.3.dist-info/WHEEL
django_minio_backend_five-3.5.3.dist-info/top_level.txt
django_minio_backend_five-3.5.3.dist-info/RECORD
