Metadata-Version: 2.1
Name: django-minio-backend-five
Version: 3.5.3
Summary: A Fork of The django-minio-backend by Kristof Daja (theriverman), provides a wrapper around the MinIO Python Library. Now with Django 5 Support
Home-page: https://github.com/theriverman/django-minio-backend
Author: Kristof Daja (theriverman)
Author-email: Habibul Rahman Qalbi <habi6799@gmail.com>
License: MIT License
Project-URL: Homepage, https://github.com/upchunk/django-minio-backend
Project-URL: Repository, https://github.com/upchunk/django-minio-backend
Keywords: django,minio,backend,django-minio,django-minio-backend,minio-backend
Classifier: Environment :: Web Environment
Classifier: Framework :: Django
Classifier: Framework :: Django :: 4.2
Classifier: Framework :: Django :: 5.0
Classifier: Intended Audience :: Developers
Classifier: License :: OSI Approved :: MIT License
Classifier: Operating System :: OS Independent
Classifier: Programming Language :: Python
Classifier: Programming Language :: Python :: 3.10
Classifier: Programming Language :: Python :: 3.11
Classifier: Topic :: Internet :: WWW/HTTP :: Dynamic Content
Classifier: Topic :: Internet :: WWW/HTTP :: Dynamic Content :: Content Management System
Classifier: Topic :: Internet :: WWW/HTTP :: WSGI :: Application
Requires-Python: >=3.10
License-File: LICENSE
Requires-Dist: Django >=4.2
Requires-Dist: minio >=7.0.2
